mugpy/__init__.py
mugpy/api.py
mugpy-0.0.1.dist-info/LICENSE
mugpy-0.0.1.dist-info/METADATA
mugpy-0.0.1.dist-info/WHEEL
mugpy-0.0.1.dist-info/top_level.txt
mugpy-0.0.1.dist-info/RECORD
