Metadata-Version: 2.1
Name: mugpy
Version: 0.0.1
Summary: A small example package
Home-page: https://github.com/joelhaasnoot/mugpy
Author: Example Author
Author-email: joelhaasnoot@gmail.com
License: UNKNOWN
Platform: UNKNOWN
Classifier: Programming Language :: Python :: 3
Classifier: License :: OSI Approved :: MIT License
Classifier: Operating System :: OS Independent
Requires-Python: >=3.6
Requires-Dist: requests
